{
    "id": 85972099,
    "name": "Shotgun",
    "author": "SpinStudios",
    "creators": [],
    "verifier": "SilverDynamix",
    "verification": "https://youtu.be/r5Pgf7ucyvM?si=Opc6TLqNXKXfKkuF",
    "showcase": "https://youtu.be/BjFjVEkfcjk?si=Ao4HX4muat4Rq1Nq",
    "percentToQualify": 100,
    "password": "159753",
    "records": [
        {
            "user": "Fizzi",
            "link": "https://youtu.be/zuDQisa-1-c?si=uo4rvPUmSgHKF6hN",
            "percent": 100,
            "fps": 288
        }
    ]
}
